<?xml version="1.0" encoding="UTF-8"?>
<objects serializationModel="Studio.02.02.00">
	<object class="AudioFile" id="{aa366757-e4d7-4cec-8f57-d5ccb5f202e7}">
		<property name="assetPath">
			<value>Boss/monster hit 4.wav</value>
		</property>
		<property name="frequencyInKHz">
			<value>48</value>
		</property>
		<property name="channelCount">
			<value>2</value>
		</property>
		<property name="length">
			<value>2</value>
		</property>
		<relationship name="masterAssetFolder">
			<destination>{317a16db-c38b-4f03-82bf-20c8dc50849c}</destination>
		</relationship>
	</object>
</objects>
